txpasslib/__init__.py
txpasslib/_threads.py
txpasslib/_version.py
txpasslib/context.py
txpasslib/test/__init__.py
txpasslib/test/doubles.py
txpasslib/test/matchers.py
txpasslib/test/test_context.py
txpasslib-0.1.0.dist-info/DESCRIPTION.rst
txpasslib-0.1.0.dist-info/METADATA
txpasslib-0.1.0.dist-info/RECORD
txpasslib-0.1.0.dist-info/WHEEL
txpasslib-0.1.0.dist-info/metadata.json
txpasslib-0.1.0.dist-info/top_level.txt
txpasslib-0.1.0.dist-info/zip-safe
